odoo/addons/purchase_supplierinfo_product_breakdown/README.rst
odoo/addons/purchase_supplierinfo_product_breakdown/__init__.py
odoo/addons/purchase_supplierinfo_product_breakdown/__manifest__.py
odoo/addons/purchase_supplierinfo_product_breakdown/data/demo.xml
odoo/addons/purchase_supplierinfo_product_breakdown/i18n/it.po
odoo/addons/purchase_supplierinfo_product_breakdown/i18n/purchase_supplierinfo_product_breakdown.pot
odoo/addons/purchase_supplierinfo_product_breakdown/models/__init__.py
odoo/addons/purchase_supplierinfo_product_breakdown/models/product_supplierinfo.py
odoo/addons/purchase_supplierinfo_product_breakdown/models/product_supplierinfo_component.py
odoo/addons/purchase_supplierinfo_product_breakdown/models/product_template.py
odoo/addons/purchase_supplierinfo_product_breakdown/models/res_partner.py
odoo/addons/purchase_supplierinfo_product_breakdown/readme/CONTRIBUTORS.rst
odoo/addons/purchase_supplierinfo_product_breakdown/readme/DESCRIPTION.rst
odoo/addons/purchase_supplierinfo_product_breakdown/readme/USAGE.rst
odoo/addons/purchase_supplierinfo_product_breakdown/security/ir.model.access.csv
odoo/addons/purchase_supplierinfo_product_breakdown/static/description/icon.png
odoo/addons/purchase_supplierinfo_product_breakdown/static/description/index.html
odoo/addons/purchase_supplierinfo_product_breakdown/tests/__init__.py
odoo/addons/purchase_supplierinfo_product_breakdown/tests/common.py
odoo/addons/purchase_supplierinfo_product_breakdown/tests/test_product_supplierinfo_component.py
odoo/addons/purchase_supplierinfo_product_breakdown/tests/test_supplierinfo.py
odoo/addons/purchase_supplierinfo_product_breakdown/views/product_supplierinfo_views.xml
odoo/addons/purchase_supplierinfo_product_breakdown/views/product_template_views.xml
odoo/addons/purchase_supplierinfo_product_breakdown/views/res_partner_views.xml
odoo14_addon_purchase_supplierinfo_product_breakdown-14.0.1.0.1.dist-info/METADATA
odoo14_addon_purchase_supplierinfo_product_breakdown-14.0.1.0.1.dist-info/WHEEL
odoo14_addon_purchase_supplierinfo_product_breakdown-14.0.1.0.1.dist-info/top_level.txt
odoo14_addon_purchase_supplierinfo_product_breakdown-14.0.1.0.1.dist-info/RECORD
